uadetector/__init__.py
uadetector/constants.py
uadetector/useragent.py
uadetector/utils.py
uadetector/wsgi.py
uadetector/django/__init__.py
uadetector/django/conf.py
uadetector/django/middleware.py
uadetector/flask/__init__.py
uadetector/pyramid/__init__.py
uadetector/tornado/__init__.py
uadetector/tornado/web.py
uadetector-0.1.3.dist-info/DESCRIPTION.rst
uadetector-0.1.3.dist-info/METADATA
uadetector-0.1.3.dist-info/RECORD
uadetector-0.1.3.dist-info/WHEEL
uadetector-0.1.3.dist-info/metadata.json
uadetector-0.1.3.dist-info/top_level.txt
