Metadata-Version: 1.1
Name: uadetector
Version: 0.1.3
Summary: WSGI Middleware and web framework extensions for handling User-Agent.
Home-page: https://github.com/tell-k/uadetector
Author: tell-k
Author-email: ffk2005@gmail.com
License: MIT
Keywords: user_agent,web,browser,detector,handling
Platform: UNKNOWN
Classifier: Development Status :: 3 - Alpha
Classifier: Environment :: Console
Classifier: Intended Audience :: Developers
Classifier: License :: OSI Approved :: MIT License
Classifier: Programming Language :: Python :: 3
Classifier: Programming Language :: Python :: 3.4
Classifier: Programming Language :: Python :: 3.5
Classifier: Programming Language :: Python :: 3.6
Classifier: Programming Language :: Python :: Implementation :: CPython
Classifier: Programming Language :: Python :: Implementation :: PyPy
Classifier: Topic :: Internet :: WWW/HTTP
Classifier: Topic :: Software Development :: Libraries
